ipyplayer/__init__.py
ipyplayer/ishazam.py
ipyplayer/pyinsta.py
ipyplayer/y2mate.py
ipyplayer/youtube/Lib.py
ipyplayer/youtube/__init__.py
ipyplayer/youtube/base.py
ipyplayer/youtube/fhandler.py
ipyplayer/youtube/models.py
ipyplayer/youtube/youtube.py
ipyplayer/youtube/config/__init__.py
iPyPlayer-0.0.0.dist-info/LICENSE
iPyPlayer-0.0.0.dist-info/METADATA
iPyPlayer-0.0.0.dist-info/WHEEL
iPyPlayer-0.0.0.dist-info/top_level.txt
iPyPlayer-0.0.0.dist-info/RECORD
