Metadata-Version: 2.1
Name: iPyPlayer
Version: 0.0.0
Summary: innovata-PyPlayer
Home-page: https://github.com/innovata/iPyPlayer
Author: innovata sambong
Author-email: iinnovata@gmail.com
Classifier: Programming Language :: Python :: 3
Classifier: License :: OSI Approved :: MIT License
Classifier: Operating System :: OS Independent
Requires-Python: >=3.9
License-File: LICENSE
Requires-Dist: instagrapi
Requires-Dist: Pillow
